bundestag/__init__.py
bundestag/fine_logging.py
bundestag/get_xlsx_uris.py
bundestag/gui.py
bundestag/paths.py
bundestag/schemas.py
bundestag/cli/__init__.py
bundestag/cli/__main__.py
bundestag/cli/download.py
bundestag/cli/transform.py
bundestag/cli/utils.py
bundestag/data/__init__.py
bundestag/data/utils.py
bundestag/data/download/__init__.py
bundestag/data/download/bundestag_sheets.py
bundestag/data/download/huggingface.py
bundestag/data/download/abgeordnetenwatch/__init__.py
bundestag/data/download/abgeordnetenwatch/cli.py
bundestag/data/download/abgeordnetenwatch/download.py
bundestag/data/download/abgeordnetenwatch/request.py
bundestag/data/download/abgeordnetenwatch/store.py
bundestag/data/transform/__init__.py
bundestag/data/transform/bundestag_sheets.py
bundestag/data/transform/abgeordnetenwatch/__init__.py
bundestag/data/transform/abgeordnetenwatch/helper.py
bundestag/data/transform/abgeordnetenwatch/transform.py
bundestag/data/transform/abgeordnetenwatch/process/__init__.py
bundestag/data/transform/abgeordnetenwatch/process/mandates.py
bundestag/data/transform/abgeordnetenwatch/process/polls.py
bundestag/data/transform/abgeordnetenwatch/process/votes.py
bundestag/ml/__init__.py
bundestag/ml/poll_clustering.py
bundestag/ml/similarity.py
bundestag/ml/vote_prediction.py
bundestag-0.1.3.dist-info/METADATA
bundestag-0.1.3.dist-info/WHEEL
bundestag-0.1.3.dist-info/entry_points.txt
bundestag-0.1.3.dist-info/licenses/LICENSE
bundestag-0.1.3.dist-info/RECORD
