Metadata-Version: 2.4
Name: bundestag
Version: 0.1.3
Summary: Download, transform and analyse roll call votes in the german federal parliament, aka the 'Bundestag'
Project-URL: Homepage, https://github.com/eschmidt42/bundestag
Project-URL: Documentation, https://eschmidt42.github.io/bundestag/
Project-URL: Repository, https://github.com/eschmidt42/bundestag
Project-URL: Issues, https://github.com/eschmidt42/bundestag/issues
Author-email: eschmidt42 <11818904+eschmidt42@users.noreply.github.com>
License:                                  Apache License
License-File: LICENSE
Classifier: Development Status :: 3 - Alpha
Classifier: Intended Audience :: Developers
Classifier: Intended Audience :: Education
Classifier: Programming Language :: Python :: 3.10
Classifier: Programming Language :: Python :: 3.11
Classifier: Programming Language :: Python :: 3.12
Classifier: Programming Language :: Python :: 3.13
Classifier: Topic :: Scientific/Engineering :: Information Analysis
Classifier: Topic :: Sociology
Requires-Python: >=3.10.0
Requires-Dist: beautifulsoup4>=4.12.2
Requires-Dist: fastexcel>=0.14.0
Requires-Dist: fastparquet>=2023.2.0
Requires-Dist: frictionless>=5.11.1
Requires-Dist: httpx>=0.28.1
Requires-Dist: matplotlib>=3.7.1
Requires-Dist: openpyxl>=3.1.2
Requires-Dist: pandas
Requires-Dist: polars>=1.32.3
Requires-Dist: pyarrow>=21.0.0
Requires-Dist: pydantic-settings>=2.10.1
Requires-Dist: pydantic>=1.10.7
Requires-Dist: rich>=12.6.0
Requires-Dist: selenium>=4.35.0
Requires-Dist: typer>=0.7.0
Requires-Dist: urllib3>=1.26.15
Requires-Dist: xlrd>=2.0.1
Requires-Dist: xlsxwriter>=3.2.5
Provides-Extra: ml
Requires-Dist: fastai>=2.7.12; extra == 'ml'
Requires-Dist: fastcore>=1.5.29; extra == 'ml'
Requires-Dist: gensim>=4.3.1; extra == 'ml'
Requires-Dist: numpy>=1.24.2; extra == 'ml'
Requires-Dist: plotnine>=0.15.0; extra == 'ml'
Requires-Dist: scikit-learn>=1.2.2; extra == 'ml'
Requires-Dist: seaborn>=0.12.2; extra == 'ml'
Requires-Dist: spacy>=3.5.2; extra == 'ml'
